azure/agrifood/__init__.py
azure_agrifood_nspkg-1.0.0.dist-info/METADATA
azure_agrifood_nspkg-1.0.0.dist-info/WHEEL
azure_agrifood_nspkg-1.0.0.dist-info/top_level.txt
azure_agrifood_nspkg-1.0.0.dist-info/RECORD
