Metadata-Version: 2.1
Name: azure-agrifood-nspkg
Version: 1.0.0
Summary: Microsoft Azure AgriFood Namespace Package [Internal]
Home-page: https://github.com/Azure/azure-sdk-for-python/
Author: Microsoft Corporation
Author-email: azurepysdk@microsoft.com
License: MIT License
Platform: UNKNOWN
Classifier: Development Status :: 5 - Production/Stable
Classifier: Programming Language :: Python
Classifier: Programming Language :: Python :: 2
Classifier: Programming Language :: Python :: 2.7
Classifier: Programming Language :: Python :: 3
Classifier: Programming Language :: Python :: 3.6
Classifier: Programming Language :: Python :: 3.7
Classifier: Programming Language :: Python :: 3.8
Classifier: Programming Language :: Python :: 3.9
Classifier: License :: OSI Approved :: MIT License
Requires-Dist: azure-nspkg (>=2.0.0)
